opentelemetry/test/__init__.py
opentelemetry/test/asgitestutil.py
opentelemetry/test/concurrency_test.py
opentelemetry/test/globals_test.py
opentelemetry/test/httptest.py
opentelemetry/test/metrictestutil.py
opentelemetry/test/mock_test_classes.py
opentelemetry/test/mock_textmap.py
opentelemetry/test/spantestutil.py
opentelemetry/test/test_base.py
opentelemetry/test/wsgitestutil.py
opentelemetry/test/version/__init__.py
opentelemetry_test_utils-0.60b1.dist-info/METADATA
opentelemetry_test_utils-0.60b1.dist-info/WHEEL
opentelemetry_test_utils-0.60b1.dist-info/RECORD
