Metadata-Version: 2.4
Name: opentelemetry-test-utils
Version: 0.60b1
Summary: Test utilities for OpenTelemetry unit tests
Project-URL: Homepage, https://github.com/open-telemetry/opentelemetry-python/tests/opentelemetry-test-utils
Project-URL: Repository, https://github.com/open-telemetry/opentelemetry-python
Author-email: OpenTelemetry Authors <cncf-opentelemetry-contributors@lists.cncf.io>
License-Expression: Apache-2.0
Classifier: Development Status :: 4 - Beta
Classifier: Framework :: OpenTelemetry
Classifier: Intended Audience :: Developers
Classifier: Programming Language :: Python
Classifier: Programming Language :: Python :: 3
Classifier: Programming Language :: Python :: 3.9
Classifier: Programming Language :: Python :: 3.10
Classifier: Programming Language :: Python :: 3.11
Classifier: Programming Language :: Python :: 3.12
Classifier: Programming Language :: Python :: 3.13
Requires-Python: >=3.9
Requires-Dist: asgiref~=3.0
Requires-Dist: opentelemetry-api==1.39.1
Requires-Dist: opentelemetry-sdk==1.39.1
